docbt/__init__.py
docbt/ai/__init__.py
docbt/ai/llm.py
docbt/cli/__init__.py
docbt/cli/docbt_cli.py
docbt/config/__init__.py
docbt/config/config.py
docbt/config/node.py
docbt/providers/__init__.py
docbt/providers/conn_bigquery.py
docbt/providers/conn_snowflake.py
docbt/server/__init__.py
docbt/server/server.py
docbt-0.1.8.dist-info/METADATA
docbt-0.1.8.dist-info/WHEEL
docbt-0.1.8.dist-info/entry_points.txt
docbt-0.1.8.dist-info/licenses/LICENSE
docbt-0.1.8.dist-info/RECORD
