Metadata-Version: 2.4
Name: docbt
Version: 0.1.8
Summary: docdbt (documentation build tool) is a Streamlit app for managing dbt project documentation.
Project-URL: Homepage, https://github.com/aleenprd/docbt
Project-URL: Repository, https://github.com/aleenprd/docbt
Project-URL: Issues, https://github.com/aleenprd/docbt/issues
Project-URL: Demo, https://docbt-demo.streamlit.app/
Author-email: Alin Preda <predaalin2694@gmail.com>
License-Expression: Apache-2.0
License-File: LICENSE
Keywords: ai,bigquery,dbt,documentation,llm,ollama,openai,snowflake,sql,streamlit,testing
Classifier: Intended Audience :: Developers
Classifier: Intended Audience :: Information Technology
Classifier: Intended Audience :: Science/Research
Classifier: License :: OSI Approved :: Apache Software License
Classifier: Operating System :: OS Independent
Classifier: Programming Language :: Python :: 3
Classifier: Topic :: Software Development :: Libraries
Requires-Python: >=3.10
Requires-Dist: click>=8.2.1
Requires-Dist: loguru>=0.7.3
Requires-Dist: openai>=1.0.0
Requires-Dist: python-dotenv>=1.1.1
Requires-Dist: pyyaml>=6.0.2
Requires-Dist: requests>=2.31.0
Requires-Dist: streamlit>=1.49.1
Requires-Dist: tiktoken>=0.5.0
Requires-Dist: watchdog>=6.0.0
Provides-Extra: all-providers
Requires-Dist: google-cloud-bigquery>=3.38.0; extra == 'all-providers'
Requires-Dist: google-cloud>=0.34.0; extra == 'all-providers'
Requires-Dist: snowflake-connector-python>=3.17.4; extra == 'all-providers'
Provides-Extra: bigquery
Requires-Dist: google-cloud-bigquery>=3.38.0; extra == 'bigquery'
Requires-Dist: google-cloud>=0.34.0; extra == 'bigquery'
Provides-Extra: snowflake
Requires-Dist: snowflake-connector-python>=3.17.4; extra == 'snowflake'
